<?xml version="1.0" encoding="UTF-8"?><tv>
<channel id="M6test">
<display-name>M6</display-name>
<icon src="https://www.programme-tv.net/imgre/fit/~2~channel~46c2dbade9ac9fed.png/480x480/quality/100/m6.png"/>
</channel>
<programme start="20260426024500 +0200" stop="20260426060000 +0200" channel="M6test">
    <title lang="fr">Programmes de la nuit</title>
    <desc lang="fr">A suivre, des rediffusions des émissions de la chaîne, ainsi que des documentaires et autres reportages destinés à divertir les couche-tard comme les lève-tôt.</desc>
    <category lang="fr">Programme</category>
    <category lang="fr">Programme indéterminé</category>
    <icon src="https://img.bouygtel.fr/CMS/images/EBE64969228A4E87CCB86326164FE0B7.jpg"/>
    <country lang="fr">France</country>
    <rating system="CSA">
      <value>Tout public</value>
    </rating>
  </programme>
<programme start="20260426060000 +0200" stop="20260426070000 +0200" channel="M6test">
    <title lang="fr">M6 Kid</title>
    <desc lang="fr">M6 Kid présente les meilleurs dessin-animés pour le plus grand bonheur de vos enfants.</desc>
    <date>2024</date>
    <category lang="fr">Magazine</category>
    <category lang="fr">Jeunesse</category>
    <icon src="https://img.bouygtel.fr/CMS/images/413EC1038F9B226BE458C1AFF3C2D407.jpg"/>
    <country lang="fr">France</country>
    <rating system="CSA">
      <value>Tout public</value>
    </rating>
  </programme>
<programme start="20260426070000 +0200" stop="20260426073000 +0200" channel="M6test">
    <title lang="fr">100% immo, l'hebdo</title>
    <desc lang="fr">Une équipe de spécialistes de l'immobilier vous dit tout sur les tendances et l'actualité du secteur immobilier,...</desc>
    <date>2026</date>
    <category lang="fr">Magazine</category>
    <category lang="fr">Découvertes</category>
    <icon src="https://img.bouygtel.fr/CMS/images/50333D59910196C347D9C3776175DEAE.jpg"/>
    <country lang="fr">France</country>
    <episode-num system="xmltv_ns">1.0.</episode-num>
    <rating system="CSA">
      <value>Tout public</value>
    </rating>
  </programme>
<programme start="20260426073000 +0200" stop="20260426102500 +0200" channel="M6test">
    <title lang="fr">My boutique Téléshop'</title>
    <desc lang="fr">Marie-Ange Nardi et Charlotte Rosier, entourées d'inventeurs, d'experts et de testeurs, dévoilent une sélection de produits astucieux, originaux et exclusifs.</desc>
    <credits>
      <guest>Marie-Ange Nardi</guest>
      <guest>Charlotte Rosier</guest>
    </credits>
    <category lang="fr">Services</category>
    <category lang="fr">Télé-achat</category>
    <icon src="https://img.bouygtel.fr/CMS/images/C6A7C904BDEAB4F3FC52C689B88B8CE3.jpg"/>
    <country lang="fr">France</country>
    <rating system="CSA">
      <value>Tout public</value>
    </rating>
  </programme>
<programme start="20260426102500 +0200" stop="20260426105500 +0200" channel="M6test">
    <title lang="fr">Turbo</title>
    <desc lang="fr">Cette semaine, Étienne Bruet et Safet Rastoder vous emmènent en Corse, terre de rallyes et de passion automobile, aux volants de deux Japonaises et une Française au tempérament bien trempé... La nouvelle Toyota Yaris GR, la Toyota Supra Ultime et l'Alpine A110 R. De belles autos, et de belles rencontres sur l'ile de beauté.</desc>
    <credits>
      <guest>Dominique Chapatte</guest>
    </credits>
    <date>2026</date>
    <category lang="fr">Loisirs</category>
    <category lang="fr">Automobilisme</category>
    <icon src="https://img.bouygtel.fr/CMS/images/5420AFB0C6C759BE0F8F1EC222D169B1.jpg"/>
    <country lang="fr">France</country>
    <rating system="CSA">
      <value>Tout public</value>
    </rating>
  </programme>
<programme start="20260426105500 +0200" stop="20260426112000 +0200" channel="M6test">
    <title lang="fr">Turbo</title>
    <desc lang="fr">Cette semaine, Safet Rastoder et Simon Potée-Gallini vous transportent au cœur de la Picardie pour vous faire découvrir un véritable paradis pour passionnés d'automobile. L'Atelier des Coteaux, ce garage d'exception, redonne vie à des véhicules a...</desc>
    <credits>
      <guest>Dominique Chapatte</guest>
    </credits>
    <date>2026</date>
    <category lang="fr">Loisirs</category>
    <category lang="fr">Automobilisme</category>
    <icon src="https://img.bouygtel.fr/CMS/images/86F891FA43881F4313C54667DAC3DBAB.jpg"/>
    <country lang="fr">France</country>
    <rating system="CSA">
      <value>Tout public</value>
    </rating>
  </programme>
<programme start="20260426112000 +0200" stop="20260426124000 +0200" channel="M6test">
    <title lang="fr">Turbo</title>
    <desc lang="fr">Cette semaine, Simon Potée-Gallini et Etienne Bruet vous emmènent au cap Ferret pour une expérience unique : le test des trois cabriolets les plus abordables du marché. Mini, Mazda MX-5 et T-Roc - trois façons différentes de conduire cheveux au vent sans se ruiner.</desc>
    <credits>
      <guest>Dominique Chapatte</guest>
    </credits>
    <date>2026</date>
    <category lang="fr">Loisirs</category>
    <category lang="fr">Automobilisme</category>
    <icon src="https://img.bouygtel.fr/CMS/images/86F891FA43881F4313C54667DAC3DBAB.jpg"/>
    <country lang="fr">France</country>
    <rating system="CSA">
      <value>Tout public</value>
    </rating>
  </programme>
<programme start="20260426124000 +0200" stop="20260426124500 +0200" channel="M6test">
    <title lang="fr">Météo</title>
    <desc lang="fr">Un bulletin détaillé et pédagogique, qui permet de connaître l'évolution de la météo au quotidien.</desc>
    <date>2026</date>
    <category lang="fr">Services</category>
    <category lang="fr">Météo</category>
    <icon src="https://img.bouygtel.fr/CMS/images/DCB6ACD4EDED5A837EF60A463FC71D04.jpg"/>
    <country lang="fr">France</country>
    <rating system="CSA">
      <value>Tout public</value>
    </rating>
  </programme>
<programme start="20260426124500 +0200" stop="20260426132500 +0200" channel="M6test">
    <title lang="fr">Le 12.45</title>
    <desc lang="fr">En 18 minutes, vous saurez tout sur l'actualité grâce à cette émission qui conjugue force des images, pédagogie dans le traitement des informations et rythme d'un journal qui va à l'essentiel.</desc>
    <credits>
      <guest>Ashley Chevalier</guest>
    </credits>
    <date>2026</date>
    <category lang="fr">Information</category>
    <category lang="fr">Journal</category>
    <icon src="https://img.bouygtel.fr/CMS/images/BF4A579BEBA708E7CE4D7D61E4503C58.jpg"/>
    <country lang="fr">France</country>
    <rating system="CSA">
      <value>Tout public</value>
    </rating>
  </programme>
<programme start="20260426132500 +0200" stop="20260426140500 +0200" channel="M6test">
    <title lang="fr">Un jour, un doc week-end</title>
    <sub-title lang="fr">Arnaques immobilières : comment s'en sortir ?</sub-title>
    <desc lang="fr">Familles, pouvoir d'achat, évasion : "Un jour, un doc week-end" propose une grande variété de documentaires et de sujets au coeur des préoccupations des Français.</desc>
    <date>2026</date>
    <category lang="fr">Magazine</category>
    <category lang="fr">Information</category>
    <icon src="https://img.bouygtel.fr/CMS/images/54BDDEE68EA876D135B6717A9F966529.jpg"/>
    <country lang="fr">France</country>
    <rating system="CSA">
      <value>Tout public</value>
    </rating>
  </programme>
<programme start="20260426140500 +0200" stop="20260426150500 +0200" channel="M6test">
    <title lang="fr">Un jour, un doc week-end</title>
    <desc lang="fr">Familles, pouvoir d'achat, évasion : "Un jour, un doc week-end" propose une grande variété de documentaires et de sujets au coeur des préoccupations des Français.</desc>
    <date>2026</date>
    <category lang="fr">Magazine</category>
    <category lang="fr">Information</category>
    <icon src="https://img.bouygtel.fr/CMS/images/804848D93F5B6CBF42CEE3CD4E4D2D0A.jpg"/>
    <country lang="fr">France</country>
    <rating system="CSA">
      <value>Tout public</value>
    </rating>
  </programme>
<programme start="20260426150500 +0200" stop="20260426160000 +0200" channel="M6test">
    <title lang="fr">Un jour, un doc week-end</title>
    <sub-title lang="fr">Rénovation : ils cassent tout pour le meilleur ! 1/2</sub-title>
    <desc lang="fr">Familles, pouvoir d'achat, évasion : "Un jour, un doc week-end" propose une grande variété de documentaires et de sujets au coeur des préoccupations des Français.</desc>
    <date>2026</date>
    <category lang="fr">Magazine</category>
    <category lang="fr">Information</category>
    <icon src="https://img.bouygtel.fr/CMS/images/6038A79652ECCEEE16D19AC4161E8E95.jpg"/>
    <country lang="fr">France</country>
    <rating system="CSA">
      <value>Tout public</value>
    </rating>
  </programme>
<programme start="20260426160000 +0200" stop="20260426171000 +0200" channel="M6test">
    <title lang="fr">Un jour, un doc week-end</title>
    <sub-title lang="fr">Rénovation : ils cassent tout pour le meilleur ! 2/2</sub-title>
    <desc lang="fr">Familles, pouvoir d'achat, évasion : "Un jour, un doc week-end" propose une grande variété de documentaires et de sujets au coeur des préoccupations des Français.</desc>
    <date>2026</date>
    <category lang="fr">Magazine</category>
    <category lang="fr">Information</category>
    <icon src="https://img.bouygtel.fr/CMS/images/6038A79652ECCEEE16D19AC4161E8E95.jpg"/>
    <country lang="fr">France</country>
    <rating system="CSA">
      <value>Tout public</value>
    </rating>
  </programme>
<programme start="20260426171000 +0200" stop="20260426184000 +0200" channel="M6test">
    <title lang="fr">66 minutes</title>
    <desc lang="fr">Des célébrités aux faits divers en passant par la politique, différents reportages reviennent sur l'actualité pour mieux l'analyser et la comprendre.</desc>
    <credits>
      <guest>Kareen Guiock Thuram</guest>
    </credits>
    <date>2026</date>
    <category lang="fr">Magazine</category>
    <category lang="fr">Information</category>
    <icon src="https://img.bouygtel.fr/CMS/images/7D922730EB9D58F4F31909005ED4391F.jpg"/>
    <country lang="fr">France</country>
    <rating system="CSA">
      <value>Tout public</value>
    </rating>
  </programme>
<programme start="20260426184000 +0200" stop="20260426194000 +0200" channel="M6test">
    <title lang="fr">66 minutes : grand format</title>
    <desc lang="fr">Décryptage d'un phénomène de société ou d'un événement tiré de l'actualité.</desc>
    <credits>
      <guest>Kareen Guiock Thuram</guest>
    </credits>
    <date>2026</date>
    <category lang="fr">Magazine</category>
    <category lang="fr">Information</category>
    <icon src="https://img.bouygtel.fr/CMS/images/F3F6E8C91FF224C9C391AEF1B05BF2BD.jpg"/>
    <country lang="fr">France</country>
    <rating system="CSA">
      <value>Tout public</value>
    </rating>
  </programme>
<programme start="20260426194000 +0200" stop="20260426194500 +0200" channel="M6test">
    <title lang="fr">Météo</title>
    <desc lang="fr">Un bulletin détaillé et pédagogique, qui permet de connaître l'évolution de la météo au quotidien.</desc>
    <date>2026</date>
    <category lang="fr">Services</category>
    <category lang="fr">Météo</category>
    <icon src="https://img.bouygtel.fr/CMS/images/CE5B606E5AE0C3A055E1DEFDE641184E.jpg"/>
    <country lang="fr">France</country>
    <rating system="CSA">
      <value>Tout public</value>
    </rating>
  </programme>
<programme start="20260426194500 +0200" stop="20260426204000 +0200" channel="M6test">
    <title lang="fr">Le 19.45</title>
    <desc lang="fr">En 18 minutes, vous saurez tout sur l'actualité grâce à cette émission qui conjugue force des images, pédagogie dans le traitement des informations et rythme d'un journal qui va à l'essentiel.</desc>
    <credits>
      <guest>Ashley Chevalier</guest>
    </credits>
    <date>2026</date>
    <category lang="fr">Information</category>
    <category lang="fr">Journal</category>
    <icon src="https://img.bouygtel.fr/CMS/images/307D64F97E714ECC1571F3C6834B2031.jpg"/>
    <country lang="fr">France</country>
    <rating system="CSA">
      <value>Tout public</value>
    </rating>
  </programme>
<programme start="20260426204000 +0200" stop="20260426211000 +0200" channel="M6test">
    <title lang="fr">E=M6</title>
    <desc lang="fr">Du château d'eau à nos robinets, l'étonnant voyage de notre eau potable ! / Chargeurs de smartphones, d'ordinateurs… les règles d'or pour bien les utiliser !</desc>
    <credits>
      <guest>Mac Lesggy</guest>
    </credits>
    <date>2026</date>
    <category lang="fr">Magazine</category>
    <category lang="fr">Sciences et technique</category>
    <icon src="https://img.bouygtel.fr/CMS/images/E88110976371C85BF52ABDD702251462.jpg"/>
    <country lang="fr">France</country>
    <rating system="CSA">
      <value>Tout public</value>
    </rating>
  </programme>
<programme start="20260426211000 +0200" stop="20260426231500 +0200" channel="M6test">
    <title lang="fr">Capital</title>
    <sub-title lang="fr">Action : nos révélations sur l'empire qui fracasse les prix</sub-title>
    <desc lang="fr">Au sommaire : Action : tous les secrets du discounter qui rend accro les Français. Comment ce petit bazar né aux Pays-Bas a-t-il mis au tapis tous ses concurrents ? - Leboncoin : comment gagner jusqu'à 3000 euros par mois ? La plateforme française est devenu un moyen de gagner beaucoup d'argent.</desc>
    <credits>
      <guest>Julien Courbet</guest>
    </credits>
    <date>2026</date>
    <category lang="fr">Magazine</category>
    <category lang="fr">Information</category>
    <icon src="https://img.bouygtel.fr/CMS/images/1641CB9599CF9174CBD0F194B3EF0232.jpg"/>
    <country lang="fr">France</country>
    <rating system="CSA">
      <value>Tout public</value>
    </rating>
  </programme>
<programme start="20260426231500 +0200" stop="20260427002500 +0200" channel="M6test">
    <title lang="fr">Enquête exclusive</title>
    <sub-title lang="fr">Corée du Nord : Kim Jong-un, le dictateur qui fait trembler la planète</sub-title>
    <desc lang="fr">Depuis quinze ans, Kim Jong-un, fantasque et cruel dictateur, règne sans partage sur le pays le plus fermé du monde et fait trembler la planète. Pour assurer la survie du régime, le paranoïaque dirigeant ne cesse de militariser la Corée du Nord, tandis que la population vit dans la plus extrême pauvreté.</desc>
    <credits>
      <guest>Bernard de La Villardière</guest>
    </credits>
    <date>2026</date>
    <category lang="fr">Magazine</category>
    <category lang="fr">Information</category>
    <icon src="https://img.bouygtel.fr/CMS/images/2CE09D8646B98CE4B118D7902C9EC988.jpg"/>
    <country lang="fr">France</country>
    <rating system="CSA">
      <value>Tout public</value>
    </rating>
  </programme>
<programme start="20260427002500 +0200" stop="20260427014500 +0200" channel="M6test">
    <title lang="fr">Enquête exclusive</title>
    <sub-title lang="fr">Turkménistan : enquête interdite au coeur d'une extravagante dictature</sub-title>
    <desc lang="fr">Situé entre l'Iran, l'Ouzbékistan et l'Afghanistan, le Turkménistan est une ex-république soviétique devenue une dictature. Le pays possède une gigantesque richesse gazière, la 4e du monde, juste derrière le Qatar. Sa capitale, Achgabat, est un délire mégalomaniaque classé ville la plus chère du monde.</desc>
    <category lang="fr">Actualites</category>
    <category lang="fr">Mag Infos</category>
    <icon src="https://thumb.canalplus.pro/http/unsafe/640x360/filters:quality(80)/img-hapi.canalplus.pro:80/ServiceImage/ImageID/116238825"/>
    <subtitles type="teletext"/>
    <rating system="CSA">
      <value>Tout public</value>
    </rating>
  </programme>
<programme start="20260427014500 +0200" stop="20260427025000 +0200" channel="M6test">
    <title lang="fr">Enquête exclusive</title>
    <sub-title lang="fr">Logements, infrastructures : la France tombe en ruine</sub-title>
    <desc lang="fr">Chaque mois, partout en France, des habitants sont évacués de chez eux en urgence car leur maison ou leur immeuble menace de s'écrouler. Il y a un peu plus de sept ans, à Marseille, la chute de deux bâtiments vétustes avait causé la mort de huit personnes. Aujourd'hui, cette gangrène gagne tous les centres-villes.</desc>
    <category lang="fr">Actualites</category>
    <category lang="fr">Mag Infos</category>
    <icon src="https://thumb.canalplus.pro/http/unsafe/640x360/filters:quality(80)/img-hapi.canalplus.pro:80/ServiceImage/ImageID/118637859"/>
    <subtitles type="teletext"/>
    <rating system="CSA">
      <value>Tout public</value>
    </rating>
  </programme>
<programme start="20260427025000 +0200" stop="20260427060000 +0200" channel="M6test">
    <title lang="fr">Programmes de la nuit</title>
    <sub-title lang="fr">Divers</sub-title>
    <desc lang="fr">A suivre, des rediffusions des émissions de la chaîne, ainsi que des documentaires et autres reportages destinés à divertir les couche-tard comme les lève-tôt.</desc>
    <category lang="fr">Divertissement</category>
    <category lang="fr">Divers</category>
    <icon src="https://thumb.canalplus.pro/http/unsafe/640x360/filters:quality(80)/img-hapi.canalplus.pro:80/ServiceImage/ImageID/120459787"/>
    <rating system="CSA">
      <value>Tout public</value>
    </rating>
  </programme>
</tv>
